{
  "target": "PUKEIPUKEI_HAMMER_8",
  "weaponId": 438,
  "category": "WEAPON_TYPE2_HAMMER",
  "elementType": "POISON",
  "assetKey": "w_w04_037",
  "grade": 8,
  "series": "SERIES_PUKEIPUKEI",
  "seriesId": 6,
  "requiredHunterRank": 1,
  "decorationSlotLevel": [
    0,
    0
  ],
  "sortOrder": 310060,
  "normalSkill": [
    {
      "skillLevelSettingId": 4201,
      "normalSkillKind": "SNEAK_ATTACK",
      "skillLevel": 1
    }
  ],
  "specialSkill": {
    "skillLevelSettingId": 5303,
    "specialSkillKind": "SPECIAL_ATTACK_HAMMER",
    "skillLevel": 3
  },
  "_levels": [
    {
      "target": "PUKEIPUKEI_HAMMER_8",
      "weaponId": 438,
      "level": 1,
      "attack": 945,
      "elementAttack": 350
    },
    {
      "target": "PUKEIPUKEI_HAMMER_8",
      "weaponId": 438,
      "level": 2,
      "attack": 992,
      "elementAttack": 354
    },
    {
      "target": "PUKEIPUKEI_HAMMER_8",
      "weaponId": 438,
      "level": 3,
      "attack": 1038,
      "elementAttack": 358
    },
    {
      "target": "PUKEIPUKEI_HAMMER_8",
      "weaponId": 438,
      "level": 4,
      "attack": 1085,
      "elementAttack": 362
    },
    {
      "target": "PUKEIPUKEI_HAMMER_8",
      "weaponId": 438,
      "level": 5,
      "attack": 1132,
      "elementAttack": 367
    }
  ],
  "_crafting": [
    {
      "target": "PUKEIPUKEI_HAMMER_8",
      "weaponId": 438,
      "craftMaterialSettingsId": 546,
      "upgrade": {
        "base": "PUKEIPUKEI_HAMMER_7",
        "baseWeaponId": 437
      },
      "_materials": {
        "id": 546,
        "zenny": 12000,
        "userItem": [
          {
            "id": 2102009,
            "num": 5
          },
          {
            "id": 1110004,
            "num": 4
          },
          {
            "id": 3001018,
            "num": 5
          }
        ]
      }
    },
    {
      "target": "PUKEIPUKEI_HAMMER_8",
      "weaponId": 438,
      "OneLevelUpFrom": 1,
      "craftMaterialSettingsId": 547,
      "_materials": {
        "id": 547,
        "zenny": 4000,
        "userItem": [
          {
            "id": 2102003,
            "num": 40
          },
          {
            "id": 2101101,
            "num": 64
          },
          {
            "id": 1010001,
            "num": 53
          },
          {
            "id": 2001009,
            "num": 4
          }
        ]
      }
    },
    {
      "target": "PUKEIPUKEI_HAMMER_8",
      "weaponId": 438,
      "OneLevelUpFrom": 2,
      "craftMaterialSettingsId": 548,
      "_materials": {
        "id": 548,
        "zenny": 6000,
        "userItem": [
          {
            "id": 2102004,
            "num": 30
          },
          {
            "id": 1110004,
            "num": 4
          },
          {
            "id": 1010002,
            "num": 40
          },
          {
            "id": 1130002,
            "num": 41
          }
        ]
      }
    },
    {
      "target": "PUKEIPUKEI_HAMMER_8",
      "weaponId": 438,
      "OneLevelUpFrom": 3,
      "craftMaterialSettingsId": 549,
      "_materials": {
        "id": 549,
        "zenny": 8000,
        "userItem": [
          {
            "id": 2102008,
            "num": 20
          },
          {
            "id": 2101101,
            "num": 64
          },
          {
            "id": 1010001,
            "num": 53
          },
          {
            "id": 2001005,
            "num": 4
          }
        ]
      }
    },
    {
      "target": "PUKEIPUKEI_HAMMER_8",
      "weaponId": 438,
      "OneLevelUpFrom": 4,
      "craftMaterialSettingsId": 550,
      "_materials": {
        "id": 550,
        "zenny": 10000,
        "userItem": [
          {
            "id": 2102001,
            "num": 100
          },
          {
            "id": 1110004,
            "num": 4
          },
          {
            "id": 1010003,
            "num": 17
          },
          {
            "id": 1140002,
            "num": 41
          }
        ]
      }
    },
    {
      "target": "PUKEIPUKEI_HAMMER_8",
      "weaponId": 438,
      "OneLevelUpFrom": 5,
      "craftMaterialSettingsId": 551,
      "_materials": {
        "id": 551,
        "zenny": 30000,
        "userItem": [
          {
            "id": 2102009,
            "num": 10
          },
          {
            "id": 1110004,
            "num": 6
          },
          {
            "id": 3001018,
            "num": 7
          }
        ]
      }
    }
  ],
  "_series": {
    "series": "SERIES_PUKEIPUKEI",
    "seriesId": 6,
    "sortOrder": 10060,
    "monsterSettingId": 3
  },
  "_skills": [
    {
      "iconId": 42,
      "level": 1,
      "descriptionKey": "SkillDescription/SNEAK_ATTACK",
      "skillConditionParameter": null,
      "skillEffectParameter": [
        10
      ]
    }
  ]
}