{
  "target": "AZURE_RATHALOS_LIGHTBOWGUN_7",
  "weaponId": 627,
  "category": "WEAPON_TYPE2_LIGHT_BOWGUN",
  "elementType": "FIRE",
  "assetKey": "w_w13_171",
  "grade": 7,
  "series": "SERIES_AZURE_RATHALOS",
  "seriesId": 19,
  "requiredHunterRank": 1,
  "decorationSlotLevel": [
    0,
    0
  ],
  "sortOrder": 510180,
  "normalSkill": [
    {
      "skillLevelSettingId": 4301,
      "normalSkillKind": "PEAK_PERFORMANCE",
      "skillLevel": 1
    }
  ],
  "specialSkill": {
    "skillLevelSettingId": 5402,
    "specialSkillKind": "SPECIAL_ATTACK_LIGHTBOWGUN",
    "skillLevel": 2
  },
  "_levels": [
    {
      "target": "AZURE_RATHALOS_LIGHTBOWGUN_7",
      "weaponId": 627,
      "level": 1,
      "attack": 753,
      "elementAttack": 248
    },
    {
      "target": "AZURE_RATHALOS_LIGHTBOWGUN_7",
      "weaponId": 627,
      "level": 2,
      "attack": 790,
      "elementAttack": 263
    },
    {
      "target": "AZURE_RATHALOS_LIGHTBOWGUN_7",
      "weaponId": 627,
      "level": 3,
      "attack": 828,
      "elementAttack": 279
    },
    {
      "target": "AZURE_RATHALOS_LIGHTBOWGUN_7",
      "weaponId": 627,
      "level": 4,
      "attack": 865,
      "elementAttack": 294
    },
    {
      "target": "AZURE_RATHALOS_LIGHTBOWGUN_7",
      "weaponId": 627,
      "level": 5,
      "attack": 902,
      "elementAttack": 310
    }
  ],
  "_crafting": [
    {
      "target": "AZURE_RATHALOS_LIGHTBOWGUN_7",
      "weaponId": 627,
      "craftMaterialSettingsId": 1521,
      "upgrade": {
        "base": "AZURE_RATHALOS_LIGHTBOWGUN_6",
        "baseWeaponId": 626
      },
      "_materials": {
        "id": 1521,
        "zenny": 6000,
        "userItem": [
          {
            "id": 2002101,
            "num": 24
          },
          {
            "id": 2002105,
            "num": 12
          },
          {
            "id": 2002106,
            "num": 3
          },
          {
            "id": 3001018,
            "num": 3
          }
        ]
      }
    },
    {
      "target": "AZURE_RATHALOS_LIGHTBOWGUN_7",
      "weaponId": 627,
      "OneLevelUpFrom": 1,
      "craftMaterialSettingsId": 1522,
      "_materials": {
        "id": 1522,
        "zenny": 2000,
        "userItem": [
          {
            "id": 2002101,
            "num": 24
          },
          {
            "id": 2101101,
            "num": 51
          },
          {
            "id": 1010001,
            "num": 42
          },
          {
            "id": 2002003,
            "num": 6
          }
        ]
      }
    },
    {
      "target": "AZURE_RATHALOS_LIGHTBOWGUN_7",
      "weaponId": 627,
      "OneLevelUpFrom": 2,
      "craftMaterialSettingsId": 1523,
      "_materials": {
        "id": 1523,
        "zenny": 3000,
        "userItem": [
          {
            "id": 2002101,
            "num": 24
          },
          {
            "id": 2002103,
            "num": 30
          },
          {
            "id": 2002104,
            "num": 20
          },
          {
            "id": 1040001,
            "num": 31
          }
        ]
      }
    },
    {
      "target": "AZURE_RATHALOS_LIGHTBOWGUN_7",
      "weaponId": 627,
      "OneLevelUpFrom": 3,
      "craftMaterialSettingsId": 1524,
      "_materials": {
        "id": 1524,
        "zenny": 4000,
        "userItem": [
          {
            "id": 2002101,
            "num": 24
          },
          {
            "id": 2101101,
            "num": 51
          },
          {
            "id": 1010001,
            "num": 42
          },
          {
            "id": 2002004,
            "num": 6
          }
        ]
      }
    },
    {
      "target": "AZURE_RATHALOS_LIGHTBOWGUN_7",
      "weaponId": 627,
      "OneLevelUpFrom": 4,
      "craftMaterialSettingsId": 1525,
      "_materials": {
        "id": 1525,
        "zenny": 5000,
        "userItem": [
          {
            "id": 2002101,
            "num": 24
          },
          {
            "id": 1010002,
            "num": 30
          },
          {
            "id": 1010003,
            "num": 11
          },
          {
            "id": 1010004,
            "num": 31
          }
        ]
      }
    },
    {
      "target": "AZURE_RATHALOS_LIGHTBOWGUN_7",
      "weaponId": 627,
      "OneLevelUpFrom": 5,
      "craftMaterialSettingsId": 1526,
      "_materials": {
        "id": 1526,
        "zenny": 12000,
        "userItem": [
          {
            "id": 2002106,
            "num": 5
          },
          {
            "id": 1110004,
            "num": 4
          },
          {
            "id": 3001018,
            "num": 5
          }
        ]
      }
    }
  ],
  "_series": {
    "series": "SERIES_AZURE_RATHALOS",
    "seriesId": 19,
    "numRequiredArmor": 40,
    "sortOrder": 10170,
    "monsterSettingId": 26
  },
  "_bowgun": {
    "target": "AZURE_RATHALOS_LIGHTBOWGUN_7",
    "weaponId": 627,
    "ammoProperty": [
      {
        "capacity": 5,
        "recoilType": "RECOIL_MEDIUM",
        "reloadType": "RELOAD_MEDIUM",
        "bowgunAmmoSettingsId": 601,
        "_ammo": {
          "id": 601,
          "ammoType": "NORMAL",
          "elementType": "FIRE",
          "level": 1,
          "htmlColorCode": "#FF7316"
        }
      },
      {
        "capacity": 4,
        "recoilType": "RECOIL_LARGE",
        "reloadType": "RELOAD_LARGE",
        "bowgunAmmoSettingsId": 1301,
        "_ammo": {
          "id": 1301,
          "ammoType": "PIERCING",
          "elementType": "FIRE",
          "level": 1,
          "iconId": 2,
          "htmlColorCode": "#FF7316"
        }
      },
      {
        "capacity": 2,
        "recoilType": "RECOIL_EXTRA_LARGE",
        "reloadType": "RELOAD_LARGE",
        "bowgunAmmoSettingsId": 2301,
        "_ammo": {
          "id": 2301,
          "ammoType": "STICKY",
          "elementType": "FIRE",
          "level": 1,
          "iconId": 3,
          "htmlColorCode": "#FF7316"
        }
      }
    ]
  },
  "_skills": [
    {
      "skillId": 43,
      "level": 1,
      "maxLevel": 5,
      "descriptionKey": "SkillDescription/PEAK_PERFORMANCE",
      "skillConditionParameter": [
        100
      ],
      "skillEffectParameter": [
        30
      ]
    }
  ]
}