{
  "target": "ORE_LANCE_4",
  "weaponId": 694,
  "category": "WEAPON_TYPE2_LANCE",
  "elementType": "NO_ELEMENT",
  "assetKey": "w_w06_010",
  "grade": 4,
  "series": "SERIES_ORE",
  "seriesId": 1,
  "requiredHunterRank": 1,
  "decorationSlotLevel": [
    0,
    0
  ],
  "sortOrder": 810010,
  "normalSkill": [
    {
      "skillLevelSettingId": 501,
      "normalSkillKind": "POISON_RESISTANCE",
      "skillLevel": 1
    }
  ],
  "specialSkill": {
    "skillLevelSettingId": 5101,
    "specialSkillKind": "SPECIAL_ATTACK_SWORDSHIELD",
    "skillLevel": 1
  },
  "_levels": [
    {
      "target": "ORE_LANCE_4",
      "weaponId": 694,
      "level": 1,
      "attack": 299
    },
    {
      "target": "ORE_LANCE_4",
      "weaponId": 694,
      "level": 2,
      "attack": 321
    },
    {
      "target": "ORE_LANCE_4",
      "weaponId": 694,
      "level": 3,
      "attack": 342
    },
    {
      "target": "ORE_LANCE_4",
      "weaponId": 694,
      "level": 4,
      "attack": 364
    },
    {
      "target": "ORE_LANCE_4",
      "weaponId": 694,
      "level": 5,
      "attack": 385
    }
  ],
  "_crafting": [
    {
      "target": "ORE_LANCE_4",
      "weaponId": 694,
      "craftMaterialSettingsId": 16,
      "upgrade": {
        "base": "ORE_LANCE_3",
        "baseWeaponId": 693
      },
      "_materials": {
        "id": 16,
        "zenny": 900,
        "userItem": [
          {
            "id": 1010001,
            "num": 18
          },
          {
            "id": 1010002,
            "num": 15
          },
          {
            "id": 1010003,
            "num": 10
          }
        ]
      }
    },
    {
      "target": "ORE_LANCE_4",
      "weaponId": 694,
      "OneLevelUpFrom": 1,
      "craftMaterialSettingsId": 17,
      "_materials": {
        "id": 17,
        "zenny": 300,
        "userItem": [
          {
            "id": 1010001,
            "num": 18
          },
          {
            "id": 2101101,
            "num": 24
          }
        ]
      }
    },
    {
      "target": "ORE_LANCE_4",
      "weaponId": 694,
      "OneLevelUpFrom": 2,
      "craftMaterialSettingsId": 18,
      "_materials": {
        "id": 18,
        "zenny": 450,
        "userItem": [
          {
            "id": 1010001,
            "num": 18
          },
          {
            "id": 1140003,
            "num": 8
          }
        ]
      }
    },
    {
      "target": "ORE_LANCE_4",
      "weaponId": 694,
      "OneLevelUpFrom": 3,
      "craftMaterialSettingsId": 19,
      "_materials": {
        "id": 19,
        "zenny": 600,
        "userItem": [
          {
            "id": 1010001,
            "num": 18
          },
          {
            "id": 2101101,
            "num": 24
          }
        ]
      }
    },
    {
      "target": "ORE_LANCE_4",
      "weaponId": 694,
      "OneLevelUpFrom": 4,
      "craftMaterialSettingsId": 20,
      "_materials": {
        "id": 20,
        "zenny": 750,
        "userItem": [
          {
            "id": 1010001,
            "num": 18
          },
          {
            "id": 1010004,
            "num": 20
          }
        ]
      }
    },
    {
      "target": "ORE_LANCE_4",
      "weaponId": 694,
      "OneLevelUpFrom": 5,
      "craftMaterialSettingsId": 441,
      "_materials": {
        "id": 441,
        "zenny": 1500,
        "userItem": [
          {
            "id": 1010001,
            "num": 24
          },
          {
            "id": 1010002,
            "num": 20
          },
          {
            "id": 1010003,
            "num": 15
          }
        ]
      }
    }
  ],
  "_series": {
    "series": "SERIES_ORE",
    "seriesId": 1,
    "sortOrder": 10010,
    "monsterSettingId": 1
  },
  "_skills": [
    {
      "skillId": 5,
      "level": 1,
      "maxLevel": 5,
      "descriptionKey": "SkillDescription/POISON_RESISTANCE_0",
      "skillConditionParameter": null,
      "skillEffectParameter": [
        20
      ]
    }
  ]
}